ironbook_a2a/__init__.py
ironbook_a2a_extension-0.0.4.dist-info/licenses/LICENSE
ironbook_a2a_extension-0.0.4.dist-info/METADATA
ironbook_a2a_extension-0.0.4.dist-info/WHEEL
ironbook_a2a_extension-0.0.4.dist-info/top_level.txt
ironbook_a2a_extension-0.0.4.dist-info/RECORD
