Metadata-Version: 2.4
Name: ironbook-a2a-extension
Version: 0.0.4
Summary: Python A2A extension for Iron Book by Identity Machines
Author-email: Identity Machines <devops@identitymachines.com>
License-Expression: MIT
Project-URL: Homepage, https://www.identitymachines.com
Project-URL: Repository, https://github.com/identitymachines/ironbook-a2a-extension
Project-URL: Documentation, https://docs.identitymachines.com
Classifier: Development Status :: 3 - Alpha
Classifier: Intended Audience :: Developers
Classifier: Programming Language :: Python :: 3
Classifier: Programming Language :: Python :: 3.8
Classifier: Programming Language :: Python :: 3.9
Classifier: Programming Language :: Python :: 3.10
Classifier: Programming Language :: Python :: 3.11
Classifier: Programming Language :: Python :: 3.12
Requires-Python: >=3.8
License-File: LICENSE
Requires-Dist: a2a-sdk>=0.3.0
Dynamic: license-file
